devart/hubspot/__init__.py
devart/hubspot/hubspot.cp39-win32.pyd
devart/hubspot/hubspot.pyi
devart/hubspot/HubSpot/Devart.Python.HubSpotEngine.dll
devart/hubspot/HubSpot/sqlite3.dll
devart/hubspot/sqlalchemy/__init__.py
devart_hubspot_connector-1.2.0.dist-info/LICENSE
devart_hubspot_connector-1.2.0.dist-info/METADATA
devart_hubspot_connector-1.2.0.dist-info/WHEEL
devart_hubspot_connector-1.2.0.dist-info/top_level.txt
devart_hubspot_connector-1.2.0.dist-info/RECORD
